Metadata-Version: 2.1
Name: ts-store
Version: 0.0.1
Summary: Flexible storage for time series.
Author-email: Martí Bosch <marti.bosch@protonmail.com>, Gionata Ghiggi <gionata.ghiggi@epfl.ch>
License: MIT
Project-URL: Repository, https://github.com/ltelab/tstore
Project-URL: homepage, https://github.com/ltelab/tstore
Project-URL: repository, https://github.com/ltelab/tstore
Project-URL: source, https://github.com/ltelab/tstore
Project-URL: tracker, https://github.com/ltelab/tstore/issues
Project-URL: documentation, https://tstore.readthedocs.io
Project-URL: changelog, https://github.com/ltelab/tstore/blob/main/CHANGELOG.md
Keywords: python,time series,storage,parquet,database
Classifier: Development Status :: 1 - Planning
Classifier: Intended Audience :: Developers
Classifier: Programming Language :: Python :: 3
Classifier: Operating System :: Unix
Classifier: Operating System :: MacOS :: MacOS X
Classifier: Operating System :: Microsoft :: Windows
Requires-Python: >=3.9
License-File: LICENSE
Requires-Dist: pandas
Requires-Dist: pyarrow
Requires-Dist: dask
Requires-Dist: distributed
Requires-Dist: polars
Requires-Dist: geopandas
Requires-Dist: pyyaml
Provides-Extra: dev
Requires-Dist: jupyter ; extra == 'dev'
Requires-Dist: pre-commit ; extra == 'dev'
Requires-Dist: pytest ; extra == 'dev'
Requires-Dist: pytest-cov ; extra == 'dev'
Requires-Dist: pytest-mock ; extra == 'dev'
Requires-Dist: pytest-sugar ; extra == 'dev'
Requires-Dist: setuptools ; extra == 'dev'
Requires-Dist: build ; extra == 'dev'
Requires-Dist: twine ; extra == 'dev'
Requires-Dist: loghub ; extra == 'dev'
